hydrusvideodeduplicator/__about__.py
hydrusvideodeduplicator/__init__.py
hydrusvideodeduplicator/__main__.py
hydrusvideodeduplicator/client.py
hydrusvideodeduplicator/config.py
hydrusvideodeduplicator/dedup.py
hydrusvideodeduplicator/dedup_util.py
hydrusvideodeduplicator/hashing.py
hydrusvideodeduplicator/page_logger.py
hydrusvideodeduplicator/typing_utils.py
hydrusvideodeduplicator/db/DedupeDB.py
hydrusvideodeduplicator/db/vptree.py
hydrusvideodeduplicator/hydrus_api/LICENSE
hydrusvideodeduplicator/hydrus_api/README.md
hydrusvideodeduplicator/hydrus_api/__init__.py
hydrusvideodeduplicator/hydrus_api/utils.py
hydrusvideodeduplicator/pdqhashing/README.md
hydrusvideodeduplicator/pdqhashing/__init__.py
hydrusvideodeduplicator/pdqhashing/hasher/__init__.py
hydrusvideodeduplicator/pdqhashing/hasher/pdq_hasher.py
hydrusvideodeduplicator/pdqhashing/pdq_types/__init__.py
hydrusvideodeduplicator/pdqhashing/pdq_types/containers.py
hydrusvideodeduplicator/pdqhashing/pdq_types/exceptions.py
hydrusvideodeduplicator/pdqhashing/pdq_types/hash256.py
hydrusvideodeduplicator/pdqhashing/tests/__init__.py
hydrusvideodeduplicator/pdqhashing/tests/hash256_test.py
hydrusvideodeduplicator/pdqhashing/tests/matrix_test.py
hydrusvideodeduplicator/pdqhashing/tests/pdq_test.py
hydrusvideodeduplicator/pdqhashing/utils/__init__.py
hydrusvideodeduplicator/pdqhashing/utils/matrix.py
hydrusvideodeduplicator/vpdqpy/__init__.py
hydrusvideodeduplicator/vpdqpy/typing_utils.py
hydrusvideodeduplicator/vpdqpy/vpdqpy.py
hydrusvideodeduplicator-0.7.0.dist-info/METADATA
hydrusvideodeduplicator-0.7.0.dist-info/WHEEL
hydrusvideodeduplicator-0.7.0.dist-info/licenses/LICENSE
hydrusvideodeduplicator-0.7.0.dist-info/RECORD
