Metadata-Version: 2.4
Name: hydrusvideodeduplicator
Version: 0.7.0
Summary: Video deduplicator utility for Hydrus Network
Project-URL: Documentation, https://github.com/hydrusvideodeduplicator/hydrus-video-deduplicator#readme
Project-URL: Issues, https://github.com/hydrusvideodeduplicator/hydrus-video-deduplicator/issues
Project-URL: Source, https://github.com/hydrusvideodeduplicator/hydrus-video-deduplicator
Author-email: hydrusvideodeduplicator <hydrusvideodeduplicator@gmail.com>
License-Expression: MIT
License-File: LICENSE
Classifier: Development Status :: 4 - Beta
Classifier: Programming Language :: Python
Classifier: Programming Language :: Python :: 3.10
Classifier: Programming Language :: Python :: 3.11
Classifier: Programming Language :: Python :: 3.12
Classifier: Programming Language :: Python :: 3.13
Requires-Python: >=3.10
Requires-Dist: av
Requires-Dist: joblib>=1.4
Requires-Dist: numpy
Requires-Dist: pillow
Requires-Dist: platformdirs
Requires-Dist: psutil
Requires-Dist: python-dotenv
Requires-Dist: requests
Requires-Dist: rich
Requires-Dist: tqdm
Requires-Dist: typer
